{
  "clients": [
    {
      "stat_value": "",
      "stat_label": "",
      "name": "Ristlin",
      "order": 1,
      "link_label": "View on Instagram",
      "link": "https://www.instagram.com/ristlin.ro",
      "image": "images/uploads/captură-de-ecran-din-2026-06-14-la-00.30.24.png",
      "description": "Emotional expression and mental health-driven ecommerce brand. Full social media management, content strategy and storytelling for Instagram - built around authenticity, not trends.",
      "services": [
        "SMM",
        "Content",
        "Brand Strategy"
      ]
    }
  ]
}
